zombie_nomnom-1.1.1.dist-info/METADATA
zombie_nomnom-1.1.1.dist-info/WHEEL
zombie_nomnom-1.1.1.dist-info/entry_points.txt
zombie_nomnom-1.1.1.dist-info/licenses/LICENSE
zombie_nomnom/__init__.py
zombie_nomnom/__main__.py
zombie_nomnom/app.py
zombie_nomnom/cli.py
zombie_nomnom/engine/__init__.py
zombie_nomnom/engine/commands.py
zombie_nomnom/engine/game.py
zombie_nomnom/engine/models.py
zombie_nomnom/engine/serialization.py
zombie_nomnom/models/__init__.py
zombie_nomnom/models/bag.py
zombie_nomnom/models/dice.py
zombie_nomnom-1.1.1.dist-info/RECORD
