Metadata-Version: 2.1
Name: zombie_nomnom
Version: 1.1.1
Summary: A Zombie Dice Game Engine Library and Executable
Keywords: game,engine,dice
Author-Email: Andres Carrera <andreshcar@live.com>
Classifier: Intended Audience :: Information Technology
Classifier: Intended Audience :: Developers
Classifier: Operating System :: OS Independent
Classifier: Topic :: Software Development :: Libraries :: Python Modules
Classifier: Topic :: Software Development :: Libraries
Classifier: Topic :: Software Development
Classifier: License :: OSI Approved :: MIT License
Classifier: Programming Language :: Python :: 3 :: Only
Classifier: Programming Language :: Python :: 3.10
Classifier: Programming Language :: Python :: 3.11
Classifier: Programming Language :: Python :: 3.12
Project-URL: Homepage, https://github.com/carrera-dev-consulting/zombie_nomnom
Project-URL: Documentation, https://consulting.gxldcptrick.dev/zombie_nomnom/docs
Project-URL: Repository, https://github.com/carrera-dev-consulting/zombie_nomnom
Project-URL: Issues, https://github.com/carrera-dev-consulting/zombie_nomnom/issues
Project-URL: Changelog, https://github.com/carrera-dev-consulting/zombie_nomnom/releases
Requires-Python: >=3.10
Requires-Dist: pydantic>=2.9.2
Requires-Dist: click>=8.1.7
